napari_bootstrapper/__init__.py
napari_bootstrapper/napari.yaml
napari_bootstrapper/widget.py
napari_bootstrapper/datasets/__init__.py
napari_bootstrapper/datasets/napari_2d_dataset.py
napari_bootstrapper/datasets/napari_3d_dataset.py
napari_bootstrapper/gp/add_2d_lsds.py
napari_bootstrapper/gp/add_obfuscated_2d_lsds.py
napari_bootstrapper/gp/calc_max_padding.py
napari_bootstrapper/gp/create_labels.py
napari_bootstrapper/gp/custom_grow_boundary.py
napari_bootstrapper/gp/custom_intensity_augment.py
napari_bootstrapper/gp/napari_image_source.py
napari_bootstrapper/gp/napari_labels_source.py
napari_bootstrapper/gp/np_source.py
napari_bootstrapper/gp/obfuscate_affs.py
napari_bootstrapper/gp/smooth_augment.py
napari_bootstrapper/gp/torch_predict.py
napari_bootstrapper/models/__init__.py
napari_bootstrapper/models/model_2d.py
napari_bootstrapper/models/model_3d.py
napari_bootstrapper/models/unet.py
napari_bootstrapper/post/__init__.py
napari_bootstrapper/post/_merge_split_widget.py
napari_bootstrapper/post/cc.py
napari_bootstrapper/post/mws.py
napari_bootstrapper/post/ws.py
napari_bootstrapper/sample_data/Fluo-C2DL-Huh7-image.tif
napari_bootstrapper/sample_data/Fluo-C2DL-Huh7-labels.tif
napari_bootstrapper/sample_data/Fluo-C2DL-Huh7-mask.tif
napari_bootstrapper/sample_data/__init__.py
napari_bootstrapper/sample_data/_load.py
napari_bootstrapper/sample_data/cremi_image.tif
napari_bootstrapper/sample_data/cremi_labels.tif
napari_bootstrapper-0.2.0.dist-info/licenses/LICENSE
napari_bootstrapper-0.2.0.dist-info/METADATA
napari_bootstrapper-0.2.0.dist-info/WHEEL
napari_bootstrapper-0.2.0.dist-info/entry_points.txt
napari_bootstrapper-0.2.0.dist-info/top_level.txt
napari_bootstrapper-0.2.0.dist-info/RECORD
