Metadata-Version: 2.4
Name: napari-bootstrapper
Version: 0.2.0
Summary: A plugin to quickly generate dense ground truth with sparse labels
Author: Vijay Venu Thiyagarajan
Author-email: vvenu@utexas.edu
License: 
Classifier: Development Status :: 2 - Pre-Alpha
Classifier: Framework :: napari
Classifier: Intended Audience :: Science/Research
Classifier: License :: OSI Approved :: BSD License
Classifier: Operating System :: OS Independent
Classifier: Programming Language :: Python
Classifier: Programming Language :: Python :: 3
Classifier: Programming Language :: Python :: 3 :: Only
Classifier: Programming Language :: Python :: 3.11
Classifier: Programming Language :: Python :: 3.12
Classifier: Programming Language :: Python :: 3.13
Classifier: Topic :: Scientific/Engineering :: Image Processing
Requires-Python: >=3.11
License-File: LICENSE
Requires-Dist: numpy
Requires-Dist: scipy
Requires-Dist: scikit-image
Requires-Dist: torch
Requires-Dist: numba
Requires-Dist: gunpowder
Requires-Dist: magicgui
Requires-Dist: qtpy
Requires-Dist: pyqtgraph
Requires-Dist: matplotlib
Requires-Dist: napari
Requires-Dist: tqdm
Requires-Dist: lsds
Requires-Dist: mwatershed
Provides-Extra: testing
Requires-Dist: tox; extra == "testing"
Requires-Dist: pytest; extra == "testing"
Requires-Dist: pytest-cov; extra == "testing"
Requires-Dist: pytest-qt; extra == "testing"
Requires-Dist: napari; extra == "testing"
Requires-Dist: pyqt5; extra == "testing"
Dynamic: license-file
